rocat/__init__.py
rocat/__main__.py
rocat/ai_functions.py
rocat/audio_utils.py
rocat/config.py
rocat/file_utils.py
rocat/image_utils.py
rocat/language_model.py
rocat/language_utils.py
rocat/main.py
rocat/template_utils.py
rocat/web_utils.py
rocat-0.2.6.dist-info/LICENSE
rocat-0.2.6.dist-info/METADATA
rocat-0.2.6.dist-info/WHEEL
rocat-0.2.6.dist-info/entry_points.txt
rocat-0.2.6.dist-info/top_level.txt
rocat-0.2.6.dist-info/RECORD
