Metadata-Version: 2.1
Name: rocat
Version: 0.2.6
Summary: A simple and user-friendly library for AI services
Home-page: https://github.com/Yumeta-Lab/rocat-dev
Author: YumetaLab
Author-email: root@yumeta.kr
Classifier: Programming Language :: Python :: 3
Classifier: License :: OSI Approved :: MIT License
Classifier: Operating System :: OS Independent
Requires-Python: >=3.6
License-File: LICENSE
Requires-Dist: altair ==5.3.0
Requires-Dist: anthropic ==0.26.1
Requires-Dist: beautifulsoup4 ==4.12.3
Requires-Dist: docx2txt ==0.8
Requires-Dist: google-search-results ==2.4.2
Requires-Dist: openai ==1.30.3
Requires-Dist: openpyxl ==3.1.2
Requires-Dist: pandas ==2.2.2
Requires-Dist: pillow ==10.3.0
Requires-Dist: pypdf ==4.2.0
Requires-Dist: python-docx ==1.1.2
Requires-Dist: python-pptx ==0.6.23
Requires-Dist: requests ==2.32.2
Requires-Dist: serpapi ==0.1.5
Requires-Dist: xlrd ==2.0.1
Requires-Dist: XlsxWriter ==3.2.0
Requires-Dist: youtube-transcript-api ==0.6.2
Requires-Dist: pycountry ==23.12.11
Requires-Dist: olefile ==0.47
